mpl_drip/__init__.py
mpl_drip/_version.py
mpl_drip/colormaps.py
mpl_drip/colors.py
mpl_drip/custom.mplstyle
mpl_drip/py.typed
mpl_drip-1.0.5.dist-info/METADATA
mpl_drip-1.0.5.dist-info/WHEEL
mpl_drip-1.0.5.dist-info/licenses/LICENSE
mpl_drip-1.0.5.dist-info/RECORD
