Metadata-Version: 2.4
Name: mpl_drip
Version: 1.0.5
Summary: Make your mpl dripped up.
Author-email: Tom Hilder <thomas.hilder@monash.edu>
License: MIT License
License-File: LICENSE
Classifier: Programming Language :: Python :: 3
Classifier: Topic :: Scientific/Engineering :: Visualization
Classifier: Typing :: Typed
Requires-Python: >=3.9
Requires-Dist: matplotlib>=3.8
